beam_sequencer/__init__.py
beam_sequencer/__main__.py
beam_sequencer/domain.py
beam_sequencer/mapper.py
beam_sequencer/options.py
beam_sequencer/pipeline.py
beam_sequencer/reducer.py
beam_sequencer/utils.py
beam_sequencer-0.1.0.dist-info/WHEEL
beam_sequencer-0.1.0.dist-info/METADATA
beam_sequencer-0.1.0.dist-info/RECORD
