Metadata-Version: 2.1
Name: beam-sequencer
Version: 0.1.0
Summary: 
Author: Yi FU
Author-email: yi.fu@hm.com
Requires-Python: >=3.8,<4.0
Classifier: Programming Language :: Python :: 3
Classifier: Programming Language :: Python :: 3.10
Classifier: Programming Language :: Python :: 3.8
Classifier: Programming Language :: Python :: 3.9
Requires-Dist: apache-beam[gcp,test] (>=2.35.0,<3.0.0)
Requires-Dist: pytest (==4.4.0)
